test1/test.v
// Russell Rodriguez
// Test Module

// Simple 4 bit memory
// Let the memory work on a clock and an enable

`timescale 1ns/1ps // need to include timescale!

// in verilator, have to make the module the same name as the file name
module test(
	input clk,
	input reset,
	input en,
	input [3:0] address,
	output reg [7:0] out
);

always@(posedge clk or negedge reset) begin
	if(!reset) out <= 8'b1000_0000; // on reset have the memory output all 0's
	else begin // output will only update 
		if(en) begin
			case(address)
				4'b0000: out <= 8'b0000_0000;
				4'b0001: out <= 8'b0000_0001;
				4'b1111: out <= 8'b0000_1111;
				default: out <= 8'b1111_1111;
			endcase
		end
	end
end


endmodule

test1/mem_tb.v
`timescale 1ns/1ps

module mem_tb;

// inputs
reg clk;
reg reset;
reg en;
reg [3:0] address;

// outputs
wire [7:0] out;

// test unit instatiation
test uut(
	.clk(clk),
	.reset(reset),
	.en(en),
	.address(address),
	.out(out)
);

// clock signal generator
initial begin
	begin: CLOCK_GENERATOR
		clk = 0;
		forever begin
			#5 clk = ~ clk;
		end
	end
end

// initial reset signal
initial begin
	#0 reset = 1;
	#20 reset = 0;
	#20 reset = 1;
	en = 1'b0;
end

initial begin
	#100;
	
	$display("Hello");
	
	@(posedge clk);
	#2 address = 4'b0000; // output should not change here since the enable is off
	#5 $display("out: %b", out);
	
	@(posedge clk);
	#2 en = 1'b1; // turns on the enable
	address = 4'b0001;
	#5 $display("out: %b", out);
	
	@(posedge clk);
	#2 address = 4'b1111;
	#5 $display("out: %b", out);
	
	@(posedge clk);
	#2 address = 4'b1010;
	#5 $display("out: %b", out);
	
	#10 $finish;
	
end

initial begin
    $dumpfile("mem_tb.vcd");
    $dumpvars(0, mem_tb);
end

endmodule

test1/mem_tb.vcd
$version Generated by VerilatedVcd $end
$timescale 1ps $end
 $scope module TOP $end
  $scope module mem_tb $end
   $var wire 1 # clk $end
   $var wire 1 $ reset $end
   $var wire 1 % en $end
   $var wire 4 & address [3:0] $end
   $var wire 8 ' out [7:0] $end
   $scope module uut $end
    $var wire 1 # clk $end
    $var wire 1 $ reset $end
    $var wire 1 % en $end
    $var wire 4 & address [3:0] $end
    $var wire 8 ' out [7:0] $end
   $upscope $end
  $upscope $end
 $upscope $end
$enddefinitions $end


#0
0#
1$
0%
b0000 &
b00000000 '
#5000
1#
#10000
0#
#15000
1#
#20000
0#
0$
b10000000 '
#25000
1#
#30000
0#
#35000
1#
#40000
0#
1$
#45000
1#
#50000
0#
#55000
1#
#60000
0#
#65000
1#
#70000
0#
#75000
1#
#80000
0#
#85000
1#
#90000
0#
#95000
1#
#100000
0#
#105000
1#
#107000
#110000
0#
#112000
#115000
1#
#117000
1%
b0001 &
#120000
0#
#122000
#125000
1#
b00000001 '
#127000
b1111 &
#130000
0#
#132000
#135000
1#
b00001111 '
#137000
b1010 &
#140000
0#
#142000
#145000
1#
b11111111 '
