test2/test2.v
`timescale 1ns/100ps // need to include timescale!

// in verilator, have to make the module the same name as the file name
module test2(
	input clk,
	input reset,
	input [7:0] data_in,
	output reg [7:0] data_out
);

always@(posedge clk or negedge reset) begin
	if(!reset) data_out <= 8'b0; // on reset have the memory output all 0's
	else data_out <= data_in; 
end

endmodule

test2/test2_waveform.vcd
$version Generated by VerilatedVcd $end
$timescale 100ps $end
 $scope module TOP $end
  $var wire 1 # clk $end
  $var wire 1 $ reset $end
  $var wire 8 % data_in [7:0] $end
  $var wire 8 & data_out [7:0] $end
  $scope module test2 $end
   $var wire 1 # clk $end
   $var wire 1 $ reset $end
   $var wire 8 % data_in [7:0] $end
   $var wire 8 & data_out [7:0] $end
  $upscope $end
 $upscope $end
$enddefinitions $end


#0
0#
0$
b00000000 %
b00000000 &
#1
1#
b00000001 %
#2
0#
b00000010 %
#3
1#
b00000011 %
#4
0#
b00000100 %
#5
1#
b00000101 %
#6
0#
b00000110 %
#7
1#
b00000111 %
#8
0#
b00001000 %
#9
1#
b00001001 %
#10
0#
b00001010 %
#11
1#
1$
b00001011 %
b00001011 &
#12
0#
b00001100 %
#13
1#
b00001101 %
b00001101 &
#14
0#
b00001110 %
#15
1#
b00001111 %
b00001111 &
#16
0#
b00010000 %
#17
1#
b00010001 %
b00010001 &
#18
0#
b00010010 %
#19
1#
b00010011 %
b00010011 &
#20
0#
b00010100 %
#21
1#
b00010101 %
b00010101 &
#22
0#
b00010110 %
#23
1#
b00010111 %
b00010111 &
#24
0#
b00011000 %
#25
1#
b00011001 %
b00011001 &
#26
0#
b00011010 %
#27
1#
b00011011 %
b00011011 &
#28
0#
b00011100 %
#29
1#
b00011101 %
b00011101 &
#30
0#
b00011110 %
#31
1#
b00011111 %
b00011111 &
#32
0#
b00100000 %
#33
1#
b00100001 %
b00100001 &
#34
0#
b00100010 %
#35
1#
b00100011 %
b00100011 &
#36
0#
b00100100 %
#37
1#
b00100101 %
b00100101 &
#38
0#
b00100110 %
#39
1#
b00100111 %
b00100111 &
#40
0#
b00101000 %
#41
1#
b00101001 %
b00101001 &
#42
0#
b00101010 %
#43
1#
b00101011 %
b00101011 &
#44
0#
b00101100 %
#45
1#
b00101101 %
b00101101 &
#46
0#
b00101110 %
#47
1#
b00101111 %
b00101111 &
#48
0#
b00110000 %
#49
1#
b00110001 %
b00110001 &
#50
0#
b00110010 %
#51
1#
b00110011 %
b00110011 &
#52
0#
b00110100 %
#53
1#
b00110101 %
b00110101 &
#54
0#
b00110110 %
#55
1#
b00110111 %
b00110111 &
#56
0#
b00111000 %
#57
1#
b00111001 %
b00111001 &
#58
0#
b00111010 %
#59
1#
b00111011 %
b00111011 &
#60
0#
b00111100 %
#61
1#
b00111101 %
b00111101 &
#62
0#
b00111110 %
#63
1#
b00111111 %
b00111111 &
#64
0#
b01000000 %
#65
1#
b01000001 %
b01000001 &
#66
0#
b01000010 %
#67
1#
b01000011 %
b01000011 &
#68
0#
b01000100 %
#69
1#
b01000101 %
b01000101 &
#70
0#
b01000110 %
#71
1#
b01000111 %
b01000111 &
#72
0#
b01001000 %
#73
1#
b01001001 %
b01001001 &
#74
0#
b01001010 %
#75
1#
b01001011 %
b01001011 &
#76
0#
b01001100 %
#77
1#
b01001101 %
b01001101 &
#78
0#
b01001110 %
#79
1#
b01001111 %
b01001111 &
#80
0#
b01010000 %
#81
1#
b01010001 %
b01010001 &
#82
0#
b01010010 %
#83
1#
b01010011 %
b01010011 &
#84
0#
b01010100 %
#85
1#
b01010101 %
b01010101 &
#86
0#
b01010110 %
#87
1#
b01010111 %
b01010111 &
#88
0#
b01011000 %
#89
1#
b01011001 %
b01011001 &
#90
0#
b01011010 %
#91
1#
b01011011 %
b01011011 &
#92
0#
b01011100 %
#93
1#
b01011101 %
b01011101 &
#94
0#
b01011110 %
#95
1#
b01011111 %
b01011111 &
#96
0#
b01100000 %
#97
1#
b01100001 %
b01100001 &
#98
0#
b01100010 %
#99
1#
b01100011 %
b01100011 &
